quickdemo/__init__.py
quickdemo/debug.py
quickdemo-0.2.0.dist-info/METADATA
quickdemo-0.2.0.dist-info/WHEEL
quickdemo-0.2.0.dist-info/top_level.txt
quickdemo-0.2.0.dist-info/RECORD
