Metadata-Version: 2.1
Name: quickdemo
Version: 0.2.0
Summary: Tiny Python library for code demonstrations and small-scale testing
Home-page: https://github.com/slyphiX/quickdemo
Author: Justus 'slyphiX' Henneberg
Author-email: slyphiX@users.noreply.github.com
License: UNKNOWN
Platform: UNKNOWN
Classifier: Development Status :: 4 - Beta
Classifier: Programming Language :: Python :: 3
Classifier: Intended Audience :: Education
Classifier: License :: Free For Educational Use
Classifier: License :: Free For Home Use
Classifier: Operating System :: OS Independent
